incomevis.py
incomevis-0.3.dist-info/LICENSE
incomevis-0.3.dist-info/METADATA
incomevis-0.3.dist-info/WHEEL
incomevis-0.3.dist-info/top_level.txt
incomevis-0.3.dist-info/RECORD
