Metadata-Version: 2.1
Name: incomevis
Version: 0.3
Summary: Visualization toolbox for income distribution
Home-page: https://github.com/sangttruong/incomevis
Author: Sang T. Truong
Author-email: sangtruong_2021@depauw.edu
License: UNKNOWN
Platform: UNKNOWN
Classifier: Programming Language :: Python :: 3
Classifier: Programming Language :: Python :: 3.6
Classifier: Programming Language :: Python :: 3.7
Classifier: Programming Language :: Python :: 3.8
Classifier: License :: OSI Approved :: MIT License
Classifier: Operating System :: OS Independent
Requires-Dist: matplotlib (>=3.0)
Requires-Dist: numpy (>=1.0)
Requires-Dist: pandas (>=1.0)
Requires-Dist: multiprocess (>=0.7)
Requires-Dist: ipython (>=5.5.0)
